tpds_extension/public_key_rotation/extension.yaml
tpds_extension/public_key_rotation/setup.py
tpds_extension/public_key_rotation/version.py
tpds_extension/public_key_rotation/TrustFlex/Public Key Rotation.ipynb
tpds_extension/public_key_rotation/TrustFlex/firmware.zip
tpds_extension/public_key_rotation/TrustFlex/pubkey_rotation.h
tpds_extension/public_key_rotation/TrustFlex/assets/Public Key Rotation.md
tpds_extension/public_key_rotation/TrustFlex/assets/Public key rotation.png
tpds_extension/public_key_rotation/TrustFlex/assets/c-snippet.png
tpds_extension/public_key_rotation/TrustFlex/assets/crypto-assets.png
tpds_extension/public_key_rotation/TrustFlex/assets/td_pubkey_rotation.png
tpds_extension/public_key_rotation/TrustFlex/assets/usecase_steps.png
tpds_extension/public_key_rotation/TrustFlex/assets/html/custom.css
tpds_extension/public_key_rotation/TrustFlex/assets/html/toggle.js
tpds_extension/public_key_rotation/TrustFlex/assets/html/images/1.png
tpds_extension/public_key_rotation/TrustFlex/assets/html/images/2-2.png
tpds_extension/public_key_rotation/TrustFlex/assets/html/images/2-3-a.png
tpds_extension/public_key_rotation/TrustFlex/assets/html/images/2-3-b.png
tpds_extension/public_key_rotation/TrustFlex/assets/html/images/2-3-d.png
tpds_extension/public_key_rotation/TrustFlex/assets/html/images/2-4.png
tpds_extension/public_key_rotation/TrustFlex/assets/html/images/Public key rotation.pptx
tpds_extension/public_key_rotation/TrustFlex/assets/html/images/Usecase.png
tpds_extension/public_key_rotation/TrustFlex/assets/html/images/authorize_public_key.png
tpds_extension/public_key_rotation/TrustFlex/assets/html/images/embedded_c_file.png
tpds_extension/public_key_rotation/TrustFlex/assets/html/images/generate_public_key.png
tpds_extension/public_key_rotation/TrustFlex/assets/html/images/make_program.png
tpds_extension/public_key_rotation/TrustFlex/assets/html/images/notebook.png
tpds_extension_spg_public_key_rotation-2.2.5.dist-info/METADATA
tpds_extension_spg_public_key_rotation-2.2.5.dist-info/WHEEL
tpds_extension_spg_public_key_rotation-2.2.5.dist-info/top_level.txt
tpds_extension_spg_public_key_rotation-2.2.5.dist-info/RECORD
