Metadata-Version: 2.1
Name: tpds-extension-spg-public-key-rotation
Version: 2.2.5
Summary: Microchip(SPG) Trust Platform - Public Key Rotation Usecase
Home-page: https://www.microchip.com/TrustPlatform
Author: Microchip Technology
Author-email: SPG.Tools@microchip.com
Classifier: License :: Other/Proprietary License
Classifier: Development Status :: 4 - Beta
Classifier: Programming Language :: Python :: 3
Classifier: Operating System :: OS Independent
Requires-Python: >=3.6
